[
  {
    "week": 1,
    "type": "PRESEASON",
    "opponent": "TEN",
    "home": true,
    "played": false,
    "scoreFor": null,
    "scoreAgainst": null,
    "result": null,
    "overtime": false,
    "attendance": 63736,
    "notes": null
  },
  {
    "week": 2,
    "type": "PRESEASON",
    "opponent": "LAC",
    "home": false,
    "played": false,
    "scoreFor": null,
    "scoreAgainst": null,
    "result": null,
    "overtime": false,
    "attendance": 61622,
    "notes": null
  },
  {
    "week": 3,
    "type": "PRESEASON",
    "opponent": "CIN",
    "home": true,
    "played": false,
    "scoreFor": null,
    "scoreAgainst": null,
    "result": null,
    "overtime": false,
    "attendance": 68398,
    "notes": null
  },
  {
    "week": 1,
    "type": "REGULAR_SEASON",
    "opponent": "NYG",
    "home": false,
    "played": false,
    "scoreFor": null,
    "scoreAgainst": null,
    "result": null,
    "overtime": false,
    "attendance": 56886,
    "notes": null
  },
  {
    "week": 2,
    "type": "REGULAR_SEASON",
    "opponent": "MIN",
    "home": true,
    "played": false,
    "scoreFor": null,
    "scoreAgainst": null,
    "result": null,
    "overtime": false,
    "attendance": 60145,
    "notes": null
  },
  {
    "week": 3,
    "type": "REGULAR_SEASON",
    "opponent": "DAL",
    "home": false,
    "played": false,
    "scoreFor": null,
    "scoreAgainst": null,
    "result": null,
    "overtime": false,
    "attendance": 60917,
    "notes": null
  },
  {
    "week": 4,
    "type": "REGULAR_SEASON",
    "opponent": "GB",
    "home": false,
    "played": false,
    "scoreFor": null,
    "scoreAgainst": null,
    "result": null,
    "overtime": false,
    "attendance": 56512,
    "notes": null
  },
  {
    "week": 5,
    "type": "REGULAR_SEASON",
    "opponent": "NYG",
    "home": true,
    "played": false,
    "scoreFor": null,
    "scoreAgainst": null,
    "result": null,
    "overtime": false,
    "attendance": 75865,
    "notes": null
  },
  {
    "week": 6,
    "type": "REGULAR_SEASON",
    "opponent": "NE",
    "home": false,
    "played": false,
    "scoreFor": null,
    "scoreAgainst": null,
    "result": null,
    "overtime": false,
    "attendance": 68186,
    "notes": null
  },
  {
    "week": 7,
    "type": "REGULAR_SEASON",
    "opponent": "CHI",
    "home": false,
    "played": false,
    "scoreFor": null,
    "scoreAgainst": null,
    "result": null,
    "overtime": false,
    "attendance": 59266,
    "notes": null
  },
  {
    "week": 8,
    "type": "REGULAR_SEASON",
    "opponent": "WAS",
    "home": true,
    "played": false,
    "scoreFor": null,
    "scoreAgainst": null,
    "result": null,
    "overtime": false,
    "attendance": 75989,
    "notes": null
  },
  {
    "week": 9,
    "type": "REGULAR_SEASON",
    "opponent": "BUF",
    "home": false,
    "played": false,
    "scoreFor": null,
    "scoreAgainst": null,
    "result": null,
    "overtime": false,
    "attendance": 72004,
    "notes": null
  },
  {
    "week": 10,
    "type": "REGULAR_SEASON",
    "opponent": "WAS",
    "home": false,
    "played": false,
    "scoreFor": null,
    "scoreAgainst": null,
    "result": null,
    "overtime": false,
    "attendance": 64013,
    "notes": null
  },
  {
    "week": 11,
    "type": "REGULAR_SEASON",
    "opponent": "SEA",
    "home": true,
    "played": false,
    "scoreFor": null,
    "scoreAgainst": null,
    "result": null,
    "overtime": false,
    "attendance": 67343,
    "notes": null
  },
  {
    "week": 12,
    "type": "REGULAR_SEASON",
    "opponent": "DAL",
    "home": true,
    "played": false,
    "scoreFor": null,
    "scoreAgainst": null,
    "result": null,
    "overtime": false,
    "attendance": 70900,
    "notes": null
  },
  {
    "week": 13,
    "type": "REGULAR_SEASON",
    "opponent": "NYJ",
    "home": true,
    "played": false,
    "scoreFor": null,
    "scoreAgainst": null,
    "result": null,
    "overtime": false,
    "attendance": 62551,
    "notes": null
  },
  {
    "week": 14,
    "type": "REGULAR_SEASON",
    "opponent": null,
    "home": false,
    "played": false,
    "scoreFor": null,
    "scoreAgainst": null,
    "result": "BYE",
    "overtime": false,
    "attendance": null,
    "notes": "Bye week"
  },
  {
    "week": 15,
    "type": "REGULAR_SEASON",
    "opponent": "NO",
    "home": true,
    "played": false,
    "scoreFor": null,
    "scoreAgainst": null,
    "result": null,
    "overtime": false,
    "attendance": 75075,
    "notes": null
  },
  {
    "week": 16,
    "type": "REGULAR_SEASON",
    "opponent": "MIA",
    "home": true,
    "played": false,
    "scoreFor": null,
    "scoreAgainst": null,
    "result": null,
    "overtime": false,
    "attendance": 74054,
    "notes": null
  },
  {
    "week": 17,
    "type": "REGULAR_SEASON",
    "opponent": "DET",
    "home": true,
    "played": false,
    "scoreFor": null,
    "scoreAgainst": null,
    "result": null,
    "overtime": false,
    "attendance": 64488,
    "notes": null
  },
  {
    "week": 18,
    "type": "REGULAR_SEASON",
    "opponent": "SEA",
    "home": true,
    "played": false,
    "scoreFor": null,
    "scoreAgainst": null,
    "result": null,
    "overtime": false,
    "attendance": 75126,
    "notes": null
  }
]